dask_ctl/__init__.py
dask_ctl/_version.py
dask_ctl/cli.py
dask_ctl/config.py
dask_ctl/ctl-schema.yaml
dask_ctl/ctl.yaml
dask_ctl/discovery.py
dask_ctl/exceptions.py
dask_ctl/lifecycle.py
dask_ctl/proxy.py
dask_ctl/renderables.py
dask_ctl/spec.py
dask_ctl/utils.py
dask_ctl/tests/specs/simple.yaml
dask_ctl/widgets/templates/snippet.py.j2
dask_ctl-2024.1.0.dist-info/LICENSE
dask_ctl-2024.1.0.dist-info/METADATA
dask_ctl-2024.1.0.dist-info/WHEEL
dask_ctl-2024.1.0.dist-info/entry_points.txt
dask_ctl-2024.1.0.dist-info/top_level.txt
dask_ctl-2024.1.0.dist-info/RECORD
