Metadata-Version: 2.1
Name: dask-ctl
Version: 2024.1.0
Summary: A set of tools to provide a control plane for managing the lifecycle of Dask clusters.
Author: Jacob Tomlinson
Author-email: jacob@tomlinson.email
Classifier: Programming Language :: Python :: 3
Classifier: License :: OSI Approved :: BSD License
Classifier: Operating System :: OS Independent
Requires-Python: >=3.9
License-File: LICENSE
Requires-Dist: click >=8.1.2
Requires-Dist: dask >=2022.11.1
Requires-Dist: distributed
Requires-Dist: numpy
Requires-Dist: rich
Requires-Dist: tornado
Requires-Dist: pyyaml
Provides-Extra: tui
Requires-Dist: textual ==0.5.0 ; extra == 'tui'
